Metadata-Version: 1.0
Name: HiveMind-chatroom
Version: 0.0.1
Summary: Mycroft Chatroom
Home-page: https://github.com/OpenJarbas/HiveMind-chatroom
Author: jarbasAI
Author-email: jarbasai@mailfence.com
License: MIT
Platform: UNKNOWN
